stew_hash/__init__.py
stew_hash/main.py
stew_hash-0.3.0.dist-info/LICENSE
stew_hash-0.3.0.dist-info/METADATA
stew_hash-0.3.0.dist-info/WHEEL
stew_hash-0.3.0.dist-info/top_level.txt
stew_hash-0.3.0.dist-info/RECORD
