Metadata-Version: 2.1
Name: stew-hash
Version: 0.3.0
Summary: A simple hashing library
Home-page: https://github.com/apinanyogaratnam/stew-hash
Author: apinanyogaratnam
Author-email: apinanapinan@icloud.com
Classifier: Programming Language :: Python :: 3
Classifier: License :: OSI Approved :: MIT License
Classifier: Operating System :: OS Independent
Requires-Python: >=3.10.4
License-File: LICENSE
